.hgignore
CHANGES.txt
LICENSE.txt
MANIFEST.in
README.txt
bootstrap.py
buildout.cfg
setup.py
js/__init__.py
js.jquery_placeholder.egg-info/PKG-INFO
js.jquery_placeholder.egg-info/SOURCES.txt
js.jquery_placeholder.egg-info/dependency_links.txt
js.jquery_placeholder.egg-info/entry_points.txt
js.jquery_placeholder.egg-info/namespace_packages.txt
js.jquery_placeholder.egg-info/not-zip-safe
js.jquery_placeholder.egg-info/requires.txt
js.jquery_placeholder.egg-info/top_level.txt
js/jquery_placeholder/__init__.py
js/jquery_placeholder/test_jquery_placeholder.txt
js/jquery_placeholder/resources/jquery.placeholder.js
js/jquery_placeholder/resources/jquery.placeholder.min.js