Metadata-Version: 1.0
Name: js.jquery-placeholder
Version: 1.3
Summary: Fanstatic packaging of jQuery Tiny Scrollbar
Home-page: https://bitbucket.org/gocept/js.jquery_placeholder
Author: gocept Developers
Author-email: mail@gocept.com
License: BSD
Platform: UNKNOWN
